mrisegmentator/__init__.py
mrisegmentator/cmdline.py
mrisegmentator/download_weights.py
mrisegmentator/inference.py
MRISegmentator-0.4.2.dist-info/METADATA
MRISegmentator-0.4.2.dist-info/WHEEL
MRISegmentator-0.4.2.dist-info/entry_points.txt
MRISegmentator-0.4.2.dist-info/top_level.txt
MRISegmentator-0.4.2.dist-info/RECORD
