Metadata-Version: 2.1
Name: MRISegmentator
Version: 0.4.2
Summary: Robust segmentation of 62 abdominal structures on MRI T1 Weighted images.
Home-page: https://github.com/rsummers11/MRISegmentator
Author: Yan Zhuang and Abhinav Suri
Author-email: rsummers@nih.gov
License: Please See Github
Classifier: Intended Audience :: Science/Research
Classifier: Programming Language :: Python
Classifier: Topic :: Scientific/Engineering
Requires-Python: >=3.9
Requires-Dist: torch >=2.0.0
Requires-Dist: tqdm >=4.45.0
Requires-Dist: p-tqdm
Requires-Dist: nnunetv2 >=2.2.1
Requires-Dist: requests
